Metadata-Version: 1.1
Name: borgweb
Version: 0.3.0
Summary: Browser-based user interface for BorgBackup
Home-page: https://borgweb.readthedocs.io/
Author: The Borg Collective (see AUTHORS file)
Author-email: borgbackup@python.org
License: BSD
Platform: Linux
Platform: MacOS X
Platform: FreeBSD
Platform: OpenBSD
Platform: NetBSD
Classifier: Development Status :: 4 - Beta
Classifier: Environment :: Console
Classifier: Intended Audience :: System Administrators
Classifier: License :: OSI Approved :: BSD License
Classifier: Operating System :: POSIX :: BSD :: FreeBSD
Classifier: Operating System :: POSIX :: BSD :: OpenBSD
Classifier: Operating System :: POSIX :: BSD :: NetBSD
Classifier: Operating System :: MacOS :: MacOS X
Classifier: Operating System :: POSIX :: Linux
Classifier: Programming Language :: Python
Classifier: Programming Language :: Python :: 3
Classifier: Programming Language :: Python :: 3.4
Classifier: Programming Language :: Python :: 3.5
Classifier: Programming Language :: Python :: 3.6
Classifier: Topic :: System :: Archiving :: Backup
